{
  "NAME": "Ім'я",
  "SURNAME": "Прізвище",
  "EMAIL": "Пошта",
  "NEXT_STEP": "Далі",
  "CHOOSE_ROLE": "Оберіть роль",
  "PASSWORD": "Пароль",
  "CONFIRM_PASSWORD": "Підтверити пароль",
  "PHONE": "Телефон",
  "INSTITUTION": "Заклад, який Ви представляєте",
  "TEACHER_BLOCK": {
    "LEARNER_NAME": "Ім'я",
    "LEARNER_SURNAME": "Прізвище",
    "LEARNER_EMAIL": "Email",
    "ADD_LEARNER": "Додати учасника"
  },
  "ROLES": {
    "JURY": "Жюрі",
    "TEACHER": "Вчитель",
    "LEARNER": "Учасник"
  }
}
